argformer/__init__.py
argformer-0.0.0.dist-info/METADATA
argformer-0.0.0.dist-info/WHEEL
argformer-0.0.0.dist-info/top_level.txt
argformer-0.0.0.dist-info/RECORD
