Metadata-Version: 2.2
Name: argformer
Version: 0.0.0
Summary: ARGformer
Author-email: David Bonet <davidbonetsole@gmail.com>
Requires-Python: >=3.8
